{"image69996499.png614713":{"filename":"image69996499.png","size":614713,"regions":[{"shape_attributes":{"name":"polyline","all_points_x":[201,349],"all_points_y":[233,391]},"region_attributes":{"name":"not_defined","type":"unknown","image_quality":{"good":true,"frontal":true,"good_illumination":true}}},{"shape_attributes":{"name":"polyline","all_points_x":[111,141],"all_points_y":[136,196]},"region_attributes":{"name":"not_defined","type":"unknown","image_quality":{"good":true,"frontal":true,"good_illumination":true}}},{"shape_attributes":{"name":"polyline","all_points_x":[288,272],"all_points_y":[127,21]},"region_attributes":{"name":"not_defined","type":"unknown","image_quality":{"good":true,"frontal":true,"good_illumination":true}}},{"shape_attributes":{"name":"polyline","all_points_x":[159,255],"all_points_y":[54,83]},"region_attributes":{"name":"not_defined","type":"unknown","image_quality":{"good":true,"frontal":true,"good_illumination":true}}},{"shape_attributes":{"name":"polyline","all_points_x":[299,374],"all_points_y":[25,90]},"region_attributes":{"name":"not_defined","type":"unknown","image_quality":{"good":true,"frontal":true,"good_illumination":true}}},{"shape_attributes":{"name":"polyline","all_points_x":[223,317],"all_points_y":[22,47]},"region_attributes":{"name":"not_defined","type":"unknown","image_quality":{"good":true,"frontal":true,"good_illumination":true}}},{"shape_attributes":{"name":"polyline","all_points_x":[146,210],"all_points_y":[433,497]},"region_attributes":{"name":"not_defined","type":"unknown","image_quality":{"good":true,"frontal":true,"good_illumination":true}}},{"shape_attributes":{"name":"polyline","all_points_x":[157,263],"all_points_y":[338,487]},"region_attributes":{"name":"not_defined","type":"unknown","image_quality":{"good":true,"frontal":true,"good_illumination":true}}},{"shape_attributes":{"name":"polyline","all_points_x":[82,159],"all_points_y":[413,491]},"region_attributes":{"name":"not_defined","type":"unknown","image_quality":{"good":true,"frontal":true,"good_illumination":true}}},{"shape_attributes":{"name":"polyline","all_points_x":[172,228],"all_points_y":[425,463]},"region_attributes":{"name":"not_defined","type":"unknown","image_quality":{"good":true,"frontal":true,"good_illumination":true}}},{"shape_attributes":{"name":"polyline","all_points_x":[76,177],"all_points_y":[446,494]},"region_attributes":{"name":"not_defined","type":"unknown","image_quality":{"good":true,"frontal":true,"good_illumination":true}}},{"shape_attributes":{"name":"polyline","all_points_x":[99,132],"all_points_y":[450,489]},"region_attributes":{"name":"not_defined","type":"unknown","image_quality":{"good":true,"frontal":true,"good_illumination":true}}},{"shape_attributes":{"name":"polyline","all_points_x":[67,83],"all_points_y":[419,489]},"region_attributes":{"name":"not_defined","type":"unknown","image_quality":{"good":true,"frontal":true,"good_illumination":true}}},{"shape_attributes":{"name":"polyline","all_points_x":[34,60],"all_points_y":[425,485]},"region_attributes":{"name":"not_defined","type":"unknown","image_quality":{"good":true,"frontal":true,"good_illumination":true}}},{"shape_attributes":{"name":"polyline","all_points_x":[23,59],"all_points_y":[449,491]},"region_attributes":{"name":"not_defined","type":"unknown","image_quality":{"good":true,"frontal":true,"good_illumination":true}}},{"shape_attributes":{"name":"polyline","all_points_x":[153,225],"all_points_y":[215,298]},"region_attributes":{"name":"not_defined","type":"unknown","image_quality":{"good":true,"frontal":true,"good_illumination":true}}},{"shape_attributes":{"name":"polyline","all_points_x":[231,319],"all_points_y":[215,274]},"region_attributes":{"name":"not_defined","type":"unknown","image_quality":{"good":true,"frontal":true,"good_illumination":true}}},{"shape_attributes":{"name":"polyline","all_points_x":[7,57],"all_points_y":[81,93]},"region_attributes":{"name":"not_defined","type":"unknown","image_quality":{"good":true,"frontal":true,"good_illumination":true}}},{"shape_attributes":{"name":"polyline","all_points_x":[131,254],"all_points_y":[131,137]},"region_attributes":{"name":"not_defined","type":"unknown","image_quality":{"good":true,"frontal":true,"good_illumination":true}}},{"shape_attributes":{"name":"polyline","all_points_x":[139,217],"all_points_y":[109,122]},"region_attributes":{"name":"not_defined","type":"unknown","image_quality":{"good":true,"frontal":true,"good_illumination":true}}},{"shape_attributes":{"name":"polyline","all_points_x":[214,317],"all_points_y":[169,241]},"region_attributes":{"name":"not_defined","type":"unknown","image_quality":{"good":true,"frontal":true,"good_illumination":true}}},{"shape_attributes":{"name":"polyline","all_points_x":[234,312],"all_points_y":[174,229]},"region_attributes":{"name":"not_defined","type":"unknown","image_quality":{"good":true,"frontal":true,"good_illumination":true}}},{"shape_attributes":{"name":"polyline","all_points_x":[369,471],"all_points_y":[336,374]},"region_attributes":{"name":"not_defined","type":"unknown","image_quality":{"good":true,"frontal":true,"good_illumination":true}}},{"shape_attributes":{"name":"polyline","all_points_x":[273,353],"all_points_y":[365,481]},"region_attributes":{"name":"not_defined","type":"unknown","image_quality":{"good":true,"frontal":true,"good_illumination":true}}},{"shape_attributes":{"name":"polyline","all_points_x":[245,257],"all_points_y":[350,417]},"region_attributes":{"name":"not_defined","type":"unknown","image_quality":{"good":true,"frontal":true,"good_illumination":true}}},{"shape_attributes":{"name":"polyline","all_points_x":[295,297],"all_points_y":[414,461]},"region_attributes":{"name":"not_defined","type":"unknown","image_quality":{"good":true,"frontal":true,"good_illumination":true}}},{"shape_attributes":{"name":"polyline","all_points_x":[258,298],"all_points_y":[385,489]},"region_attributes":{"name":"not_defined","type":"unknown","image_quality":{"good":true,"frontal":true,"good_illumination":true}}},{"shape_attributes":{"name":"polyline","all_points_x":[66,114],"all_points_y":[275,260]},"region_attributes":{"name":"not_defined","type":"unknown","image_quality":{"good":true,"frontal":true,"good_illumination":true}}},{"shape_attributes":{"name":"polyline","all_points_x":[20,49],"all_points_y":[270,277]},"region_attributes":{"name":"not_defined","type":"unknown","image_quality":{"good":true,"frontal":true,"good_illumination":true}}},{"shape_attributes":{"name":"polyline","all_points_x":[110,180],"all_points_y":[360,385]},"region_attributes":{"name":"not_defined","type":"unknown","image_quality":{"good":true,"frontal":true,"good_illumination":true}}},{"shape_attributes":{"name":"polyline","all_points_x":[289,331],"all_points_y":[333,403]},"region_attributes":{"name":"not_defined","type":"unknown","image_quality":{"good":true,"frontal":true,"good_illumination":true}}},{"shape_attributes":{"name":"polyline","all_points_x":[341,377],"all_points_y":[417,463]},"region_attributes":{"name":"not_defined","type":"unknown","image_quality":{"good":true,"frontal":true,"good_illumination":true}}},{"shape_attributes":{"name":"polyline","all_points_x":[337,413],"all_points_y":[400,475]},"region_attributes":{"name":"not_defined","type":"unknown","image_quality":{"good":true,"frontal":true,"good_illumination":true}}},{"shape_attributes":{"name":"polyline","all_points_x":[370,447],"all_points_y":[420,498]},"region_attributes":{"name":"not_defined","type":"unknown","image_quality":{"good":true,"frontal":true,"good_illumination":true}}},{"shape_attributes":{"name":"polyline","all_points_x":[405,475],"all_points_y":[451,495]},"region_attributes":{"name":"not_defined","type":"unknown","image_quality":{"good":true,"frontal":true,"good_illumination":true}}},{"shape_attributes":{"name":"polyline","all_points_x":[299,349],"all_points_y":[285,327]},"region_attributes":{"name":"not_defined","type":"unknown","image_quality":{"good":true,"frontal":true,"good_illumination":true}}},{"shape_attributes":{"name":"polyline","all_points_x":[333,477],"all_points_y":[305,364]},"region_attributes":{"name":"not_defined","type":"unknown","image_quality":{"good":true,"frontal":true,"good_illumination":true}}},{"shape_attributes":{"name":"polyline","all_points_x":[364,427],"all_points_y":[325,377]},"region_attributes":{"name":"not_defined","type":"unknown","image_quality":{"good":true,"frontal":true,"good_illumination":true}}},{"shape_attributes":{"name":"polyline","all_points_x":[324,479],"all_points_y":[287,371]},"region_attributes":{"name":"not_defined","type":"unknown","image_quality":{"good":true,"frontal":true,"good_illumination":true}}},{"shape_attributes":{"name":"polyline","all_points_x":[335,405],"all_points_y":[235,307]},"region_attributes":{"name":"not_defined","type":"unknown","image_quality":{"good":true,"frontal":true,"good_illumination":true}}},{"shape_attributes":{"name":"polyline","all_points_x":[322,369],"all_points_y":[267,306]},"region_attributes":{"name":"not_defined","type":"unknown","image_quality":{"good":true,"frontal":true,"good_illumination":true}}},{"shape_attributes":{"name":"polyline","all_points_x":[292,447],"all_points_y":[173,317]},"region_attributes":{"name":"not_defined","type":"unknown","image_quality":{"good":true,"frontal":true,"good_illumination":true}}},{"shape_attributes":{"name":"polyline","all_points_x":[299,369],"all_points_y":[156,238]},"region_attributes":{"name":"not_defined","type":"unknown","image_quality":{"good":true,"frontal":true,"good_illumination":true}}},{"shape_attributes":{"name":"polyline","all_points_x":[225,314],"all_points_y":[223,184]},"region_attributes":{"name":"not_defined","type":"unknown","image_quality":{"good":true,"frontal":true,"good_illumination":true}}},{"shape_attributes":{"name":"polyline","all_points_x":[342,389],"all_points_y":[16,74]},"region_attributes":{"name":"not_defined","type":"unknown","image_quality":{"good":true,"frontal":true,"good_illumination":true}}},{"shape_attributes":{"name":"polyline","all_points_x":[305,375],"all_points_y":[2,74]},"region_attributes":{"name":"not_defined","type":"unknown","image_quality":{"good":true,"frontal":true,"good_illumination":true}}},{"shape_attributes":{"name":"polyline","all_points_x":[427,487],"all_points_y":[136,159]},"region_attributes":{"name":"not_defined","type":"unknown","image_quality":{"good":true,"frontal":true,"good_illumination":true}}},{"shape_attributes":{"name":"polyline","all_points_x":[348,392],"all_points_y":[177,150]},"region_attributes":{"name":"not_defined","type":"unknown","image_quality":{"good":true,"frontal":true,"good_illumination":true}}},{"shape_attributes":{"name":"polyline","all_points_x":[394,480],"all_points_y":[167,192]},"region_attributes":{"name":"not_defined","type":"unknown","image_quality":{"good":true,"frontal":true,"good_illumination":true}}},{"shape_attributes":{"name":"polyline","all_points_x":[429,499],"all_points_y":[266,303]},"region_attributes":{"name":"not_defined","type":"unknown","image_quality":{"good":true,"frontal":true,"good_illumination":true}}},{"shape_attributes":{"name":"polyline","all_points_x":[470,437],"all_points_y":[211,263]},"region_attributes":{"name":"not_defined","type":"unknown","image_quality":{"good":true,"frontal":true,"good_illumination":true}}},{"shape_attributes":{"name":"polyline","all_points_x":[403,482],"all_points_y":[233,273]},"region_attributes":{"name":"not_defined","type":"unknown","image_quality":{"good":true,"frontal":true,"good_illumination":true}}},{"shape_attributes":{"name":"polyline","all_points_x":[438,493],"all_points_y":[233,274]},"region_attributes":{"name":"not_defined","type":"unknown","image_quality":{"good":true,"frontal":true,"good_illumination":true}}},{"shape_attributes":{"name":"polyline","all_points_x":[358,388],"all_points_y":[163,184]},"region_attributes":{"name":"not_defined","type":"unknown","image_quality":{"good":true,"frontal":true,"good_illumination":true}}},{"shape_attributes":{"name":"polyline","all_points_x":[380,360],"all_points_y":[131,213]},"region_attributes":{"name":"not_defined","type":"unknown","image_quality":{"good":true,"frontal":true,"good_illumination":true}}},{"shape_attributes":{"name":"polyline","all_points_x":[389,417],"all_points_y":[12,41]},"region_attributes":{"name":"not_defined","type":"unknown","image_quality":{"good":true,"frontal":true,"good_illumination":true}}},{"shape_attributes":{"name":"polyline","all_points_x":[347,396],"all_points_y":[16,63]},"region_attributes":{"name":"not_defined","type":"unknown","image_quality":{"good":true,"frontal":true,"good_illumination":true}}},{"shape_attributes":{"name":"polyline","all_points_x":[361,395],"all_points_y":[63,59]},"region_attributes":{"name":"not_defined","type":"unknown","image_quality":{"good":true,"frontal":true,"good_illumination":true}}},{"shape_attributes":{"name":"polyline","all_points_x":[465,496],"all_points_y":[134,150]},"region_attributes":{"name":"not_defined","type":"unknown","image_quality":{"good":true,"frontal":true,"good_illumination":true}}},{"shape_attributes":{"name":"polyline","all_points_x":[437,491],"all_points_y":[207,219]},"region_attributes":{"name":"not_defined","type":"unknown","image_quality":{"good":true,"frontal":true,"good_illumination":true}}},{"shape_attributes":{"name":"polyline","all_points_x":[99,194],"all_points_y":[23,53]},"region_attributes":{"name":"not_defined","type":"unknown","image_quality":{"good":true,"frontal":true,"good_illumination":true}}},{"shape_attributes":{"name":"polyline","all_points_x":[198,223],"all_points_y":[406,450]},"region_attributes":{"name":"not_defined","type":"unknown","image_quality":{"good":true,"frontal":true,"good_illumination":true}}}],"file_attributes":{"caption":"","public_domain":"no","image_url":""}}}