{"image89998499.png617779":{"filename":"image89998499.png","size":617779,"regions":[{"shape_attributes":{"name":"polyline","all_points_x":[236,271],"all_points_y":[148,60]},"region_attributes":{"name":"not_defined","type":"unknown","image_quality":{"good":true,"frontal":true,"good_illumination":true}}},{"shape_attributes":{"name":"polyline","all_points_x":[407,373],"all_points_y":[164,32]},"region_attributes":{"name":"not_defined","type":"unknown","image_quality":{"good":true,"frontal":true,"good_illumination":true}}},{"shape_attributes":{"name":"polyline","all_points_x":[498,449],"all_points_y":[53,14]},"region_attributes":{"name":"not_defined","type":"unknown","image_quality":{"good":true,"frontal":true,"good_illumination":true}}},{"shape_attributes":{"name":"polyline","all_points_x":[423,418],"all_points_y":[213,130]},"region_attributes":{"name":"not_defined","type":"unknown","image_quality":{"good":true,"frontal":true,"good_illumination":true}}},{"shape_attributes":{"name":"polyline","all_points_x":[362,337],"all_points_y":[239,158]},"region_attributes":{"name":"not_defined","type":"unknown","image_quality":{"good":true,"frontal":true,"good_illumination":true}}},{"shape_attributes":{"name":"polyline","all_points_x":[321,326],"all_points_y":[243,175]},"region_attributes":{"name":"not_defined","type":"unknown","image_quality":{"good":true,"frontal":true,"good_illumination":true}}},{"shape_attributes":{"name":"polyline","all_points_x":[307,314],"all_points_y":[183,140]},"region_attributes":{"name":"not_defined","type":"unknown","image_quality":{"good":true,"frontal":true,"good_illumination":true}}},{"shape_attributes":{"name":"polyline","all_points_x":[342,308],"all_points_y":[260,230]},"region_attributes":{"name":"not_defined","type":"unknown","image_quality":{"good":true,"frontal":true,"good_illumination":true}}},{"shape_attributes":{"name":"polyline","all_points_x":[299,249],"all_points_y":[216,154]},"region_attributes":{"name":"not_defined","type":"unknown","image_quality":{"good":true,"frontal":true,"good_illumination":true}}},{"shape_attributes":{"name":"polyline","all_points_x":[302,227],"all_points_y":[250,148]},"region_attributes":{"name":"not_defined","type":"unknown","image_quality":{"good":true,"frontal":true,"good_illumination":true}}},{"shape_attributes":{"name":"polyline","all_points_x":[277,199],"all_points_y":[248,165]},"region_attributes":{"name":"not_defined","type":"unknown","image_quality":{"good":true,"frontal":true,"good_illumination":true}}},{"shape_attributes":{"name":"polyline","all_points_x":[222,190],"all_points_y":[207,158]},"region_attributes":{"name":"not_defined","type":"unknown","image_quality":{"good":true,"frontal":true,"good_illumination":true}}},{"shape_attributes":{"name":"polyline","all_points_x":[196,160],"all_points_y":[160,112]},"region_attributes":{"name":"not_defined","type":"unknown","image_quality":{"good":true,"frontal":true,"good_illumination":true}}},{"shape_attributes":{"name":"polyline","all_points_x":[58,107],"all_points_y":[209,138]},"region_attributes":{"name":"not_defined","type":"unknown","image_quality":{"good":true,"frontal":true,"good_illumination":true}}},{"shape_attributes":{"name":"polyline","all_points_x":[119,45],"all_points_y":[181,102]},"region_attributes":{"name":"not_defined","type":"unknown","image_quality":{"good":true,"frontal":true,"good_illumination":true}}},{"shape_attributes":{"name":"polyline","all_points_x":[77,50],"all_points_y":[96,53]},"region_attributes":{"name":"not_defined","type":"unknown","image_quality":{"good":true,"frontal":true,"good_illumination":true}}},{"shape_attributes":{"name":"polyline","all_points_x":[102,77],"all_points_y":[88,30]},"region_attributes":{"name":"not_defined","type":"unknown","image_quality":{"good":true,"frontal":true,"good_illumination":true}}},{"shape_attributes":{"name":"polyline","all_points_x":[183,149],"all_points_y":[230,116]},"region_attributes":{"name":"not_defined","type":"unknown","image_quality":{"good":true,"frontal":true,"good_illumination":true}}},{"shape_attributes":{"name":"polyline","all_points_x":[168,145],"all_points_y":[248,178]},"region_attributes":{"name":"not_defined","type":"unknown","image_quality":{"good":true,"frontal":true,"good_illumination":true}}},{"shape_attributes":{"name":"polyline","all_points_x":[147,124],"all_points_y":[253,172]},"region_attributes":{"name":"not_defined","type":"unknown","image_quality":{"good":true,"frontal":true,"good_illumination":true}}},{"shape_attributes":{"name":"polyline","all_points_x":[82,56],"all_points_y":[211,132]},"region_attributes":{"name":"not_defined","type":"unknown","image_quality":{"good":true,"frontal":true,"good_illumination":true}}},{"shape_attributes":{"name":"polyline","all_points_x":[108,111],"all_points_y":[100,59]},"region_attributes":{"name":"not_defined","type":"unknown","image_quality":{"good":true,"frontal":true,"good_illumination":true}}},{"shape_attributes":{"name":"polyline","all_points_x":[61,43],"all_points_y":[246,172]},"region_attributes":{"name":"not_defined","type":"unknown","image_quality":{"good":true,"frontal":true,"good_illumination":true}}},{"shape_attributes":{"name":"polyline","all_points_x":[75,49],"all_points_y":[239,177]},"region_attributes":{"name":"not_defined","type":"unknown","image_quality":{"good":true,"frontal":true,"good_illumination":true}}},{"shape_attributes":{"name":"polyline","all_points_x":[39,27],"all_points_y":[162,92]},"region_attributes":{"name":"not_defined","type":"unknown","image_quality":{"good":true,"frontal":true,"good_illumination":true}}},{"shape_attributes":{"name":"polyline","all_points_x":[36,28],"all_points_y":[276,149]},"region_attributes":{"name":"not_defined","type":"unknown","image_quality":{"good":true,"frontal":true,"good_illumination":true}}},{"shape_attributes":{"name":"polyline","all_points_x":[29,11],"all_points_y":[133,44]},"region_attributes":{"name":"not_defined","type":"unknown","image_quality":{"good":true,"frontal":true,"good_illumination":true}}},{"shape_attributes":{"name":"polyline","all_points_x":[125,109],"all_points_y":[224,188]},"region_attributes":{"name":"not_defined","type":"unknown","image_quality":{"good":true,"frontal":true,"good_illumination":true}}},{"shape_attributes":{"name":"polyline","all_points_x":[263,198],"all_points_y":[290,210]},"region_attributes":{"name":"not_defined","type":"unknown","image_quality":{"good":true,"frontal":true,"good_illumination":true}}},{"shape_attributes":{"name":"polyline","all_points_x":[214,175],"all_points_y":[267,178]},"region_attributes":{"name":"not_defined","type":"unknown","image_quality":{"good":true,"frontal":true,"good_illumination":true}}},{"shape_attributes":{"name":"polyline","all_points_x":[236,203],"all_points_y":[271,223]},"region_attributes":{"name":"not_defined","type":"unknown","image_quality":{"good":true,"frontal":true,"good_illumination":true}}},{"shape_attributes":{"name":"polyline","all_points_x":[389,287],"all_points_y":[309,270]},"region_attributes":{"name":"not_defined","type":"unknown","image_quality":{"good":true,"frontal":true,"good_illumination":true}}},{"shape_attributes":{"name":"polyline","all_points_x":[381,285],"all_points_y":[378,312]},"region_attributes":{"name":"not_defined","type":"unknown","image_quality":{"good":true,"frontal":true,"good_illumination":true}}},{"shape_attributes":{"name":"polyline","all_points_x":[375,306],"all_points_y":[407,341]},"region_attributes":{"name":"not_defined","type":"unknown","image_quality":{"good":true,"frontal":true,"good_illumination":true}}},{"shape_attributes":{"name":"polyline","all_points_x":[388,382],"all_points_y":[413,370]},"region_attributes":{"name":"not_defined","type":"unknown","image_quality":{"good":true,"frontal":true,"good_illumination":true}}},{"shape_attributes":{"name":"polyline","all_points_x":[459,466],"all_points_y":[213,126]},"region_attributes":{"name":"not_defined","type":"unknown","image_quality":{"good":true,"frontal":true,"good_illumination":true}}},{"shape_attributes":{"name":"polyline","all_points_x":[482,439],"all_points_y":[200,148]},"region_attributes":{"name":"not_defined","type":"unknown","image_quality":{"good":true,"frontal":true,"good_illumination":true}}},{"shape_attributes":{"name":"polyline","all_points_x":[431,401],"all_points_y":[138,98]},"region_attributes":{"name":"not_defined","type":"unknown","image_quality":{"good":true,"frontal":true,"good_illumination":true}}},{"shape_attributes":{"name":"polyline","all_points_x":[498,460],"all_points_y":[396,328]},"region_attributes":{"name":"not_defined","type":"unknown","image_quality":{"good":true,"frontal":true,"good_illumination":true}}},{"shape_attributes":{"name":"polyline","all_points_x":[478,446],"all_points_y":[380,329]},"region_attributes":{"name":"not_defined","type":"unknown","image_quality":{"good":true,"frontal":true,"good_illumination":true}}},{"shape_attributes":{"name":"polyline","all_points_x":[456,386],"all_points_y":[356,246]},"region_attributes":{"name":"not_defined","type":"unknown","image_quality":{"good":true,"frontal":true,"good_illumination":true}}},{"shape_attributes":{"name":"polyline","all_points_x":[376,347],"all_points_y":[232,164]},"region_attributes":{"name":"not_defined","type":"unknown","image_quality":{"good":true,"frontal":true,"good_illumination":true}}},{"shape_attributes":{"name":"polyline","all_points_x":[266,228],"all_points_y":[352,310]},"region_attributes":{"name":"not_defined","type":"unknown","image_quality":{"good":true,"frontal":true,"good_illumination":true}}},{"shape_attributes":{"name":"polyline","all_points_x":[254,221],"all_points_y":[323,277]},"region_attributes":{"name":"not_defined","type":"unknown","image_quality":{"good":true,"frontal":true,"good_illumination":true}}},{"shape_attributes":{"name":"polyline","all_points_x":[219,187],"all_points_y":[300,263]},"region_attributes":{"name":"not_defined","type":"unknown","image_quality":{"good":true,"frontal":true,"good_illumination":true}}},{"shape_attributes":{"name":"polyline","all_points_x":[213,173],"all_points_y":[346,282]},"region_attributes":{"name":"not_defined","type":"unknown","image_quality":{"good":true,"frontal":true,"good_illumination":true}}},{"shape_attributes":{"name":"polyline","all_points_x":[249,164],"all_points_y":[432,310]},"region_attributes":{"name":"not_defined","type":"unknown","image_quality":{"good":true,"frontal":true,"good_illumination":true}}},{"shape_attributes":{"name":"polyline","all_points_x":[232,200],"all_points_y":[397,283]},"region_attributes":{"name":"not_defined","type":"unknown","image_quality":{"good":true,"frontal":true,"good_illumination":true}}},{"shape_attributes":{"name":"polyline","all_points_x":[362,307],"all_points_y":[499,418]},"region_attributes":{"name":"not_defined","type":"unknown","image_quality":{"good":true,"frontal":true,"good_illumination":true}}},{"shape_attributes":{"name":"polyline","all_points_x":[348,251],"all_points_y":[497,389]},"region_attributes":{"name":"not_defined","type":"unknown","image_quality":{"good":true,"frontal":true,"good_illumination":true}}},{"shape_attributes":{"name":"polyline","all_points_x":[235,208],"all_points_y":[432,381]},"region_attributes":{"name":"not_defined","type":"unknown","image_quality":{"good":true,"frontal":true,"good_illumination":true}}},{"shape_attributes":{"name":"polyline","all_points_x":[218,168],"all_points_y":[413,338]},"region_attributes":{"name":"not_defined","type":"unknown","image_quality":{"good":true,"frontal":true,"good_illumination":true}}},{"shape_attributes":{"name":"polyline","all_points_x":[150,96],"all_points_y":[365,295]},"region_attributes":{"name":"not_defined","type":"unknown","image_quality":{"good":true,"frontal":true,"good_illumination":true}}},{"shape_attributes":{"name":"polyline","all_points_x":[161,122],"all_points_y":[391,331]},"region_attributes":{"name":"not_defined","type":"unknown","image_quality":{"good":true,"frontal":true,"good_illumination":true}}},{"shape_attributes":{"name":"polyline","all_points_x":[96,75],"all_points_y":[293,271]},"region_attributes":{"name":"not_defined","type":"unknown","image_quality":{"good":true,"frontal":true,"good_illumination":true}}},{"shape_attributes":{"name":"polyline","all_points_x":[93,83],"all_points_y":[285,248]},"region_attributes":{"name":"not_defined","type":"unknown","image_quality":{"good":true,"frontal":true,"good_illumination":true}}},{"shape_attributes":{"name":"polyline","all_points_x":[111,90],"all_points_y":[319,247]},"region_attributes":{"name":"not_defined","type":"unknown","image_quality":{"good":true,"frontal":true,"good_illumination":true}}},{"shape_attributes":{"name":"polyline","all_points_x":[139,113],"all_points_y":[392,325]},"region_attributes":{"name":"not_defined","type":"unknown","image_quality":{"good":true,"frontal":true,"good_illumination":true}}},{"shape_attributes":{"name":"polyline","all_points_x":[96,1],"all_points_y":[342,196]},"region_attributes":{"name":"not_defined","type":"unknown","image_quality":{"good":true,"frontal":true,"good_illumination":true}}},{"shape_attributes":{"name":"polyline","all_points_x":[88,2],"all_points_y":[351,230]},"region_attributes":{"name":"not_defined","type":"unknown","image_quality":{"good":true,"frontal":true,"good_illumination":true}}},{"shape_attributes":{"name":"polyline","all_points_x":[184,119],"all_points_y":[466,401]},"region_attributes":{"name":"not_defined","type":"unknown","image_quality":{"good":true,"frontal":true,"good_illumination":true}}},{"shape_attributes":{"name":"polyline","all_points_x":[220,201],"all_points_y":[500,475]},"region_attributes":{"name":"not_defined","type":"unknown","image_quality":{"good":true,"frontal":true,"good_illumination":true}}},{"shape_attributes":{"name":"polyline","all_points_x":[176,42],"all_points_y":[471,347]},"region_attributes":{"name":"not_defined","type":"unknown","image_quality":{"good":true,"frontal":true,"good_illumination":true}}},{"shape_attributes":{"name":"polyline","all_points_x":[76,13],"all_points_y":[356,289]},"region_attributes":{"name":"not_defined","type":"unknown","image_quality":{"good":true,"frontal":true,"good_illumination":true}}},{"shape_attributes":{"name":"polyline","all_points_x":[99,5],"all_points_y":[427,350]},"region_attributes":{"name":"not_defined","type":"unknown","image_quality":{"good":true,"frontal":true,"good_illumination":true}}},{"shape_attributes":{"name":"polyline","all_points_x":[113,5],"all_points_y":[491,400]},"region_attributes":{"name":"not_defined","type":"unknown","image_quality":{"good":true,"frontal":true,"good_illumination":true}}},{"shape_attributes":{"name":"polyline","all_points_x":[72,30],"all_points_y":[439,398]},"region_attributes":{"name":"not_defined","type":"unknown","image_quality":{"good":true,"frontal":true,"good_illumination":true}}},{"shape_attributes":{"name":"polyline","all_points_x":[124,95],"all_points_y":[453,427]},"region_attributes":{"name":"not_defined","type":"unknown","image_quality":{"good":true,"frontal":true,"good_illumination":true}}},{"shape_attributes":{"name":"polyline","all_points_x":[89,16],"all_points_y":[499,435]},"region_attributes":{"name":"not_defined","type":"unknown","image_quality":{"good":true,"frontal":true,"good_illumination":true}}},{"shape_attributes":{"name":"polyline","all_points_x":[59,5],"all_points_y":[468,419]},"region_attributes":{"name":"not_defined","type":"unknown","image_quality":{"good":true,"frontal":true,"good_illumination":true}}},{"shape_attributes":{"name":"polyline","all_points_x":[62,14],"all_points_y":[497,449]},"region_attributes":{"name":"not_defined","type":"unknown","image_quality":{"good":true,"frontal":true,"good_illumination":true}}},{"shape_attributes":{"name":"polyline","all_points_x":[80,36],"all_points_y":[498,459]},"region_attributes":{"name":"not_defined","type":"unknown","image_quality":{"good":true,"frontal":true,"good_illumination":true}}},{"shape_attributes":{"name":"polyline","all_points_x":[494,400],"all_points_y":[269,196]},"region_attributes":{"name":"not_defined","type":"unknown","image_quality":{"good":true,"frontal":true,"good_illumination":true}}},{"shape_attributes":{"name":"polyline","all_points_x":[395,401],"all_points_y":[402,349]},"region_attributes":{"name":"not_defined","type":"unknown","image_quality":{"good":true,"frontal":true,"good_illumination":true}}},{"shape_attributes":{"name":"polyline","all_points_x":[445,340],"all_points_y":[397,311]},"region_attributes":{"name":"not_defined","type":"unknown","image_quality":{"good":true,"frontal":true,"good_illumination":true}}}],"file_attributes":{"caption":"","public_domain":"no","image_url":""}}}